LICENSE
MANIFEST.in
README.md
pyproject.toml
src/jade/__init__.py
src/jade.egg-info/PKG-INFO
src/jade.egg-info/SOURCES.txt
src/jade.egg-info/dependency_links.txt
src/jade.egg-info/entry_points.txt
src/jade.egg-info/requires.txt
src/jade.egg-info/top_level.txt
src/jade/JADE_launch/__init__.py
src/jade/JADE_mainproc/__init__.py
src/jade/JADE_postproc/__init__.py
src/jade/JADE_preproc/__init__.py