Metadata-Version: 2.1
Name: jade
Version: 0.1.0
Summary: Exoplanet evolution code
Author: 
Author-email: "O. Attia and V. Bourrier" <vincent.bourrier@unige.ch>
Project-URL: Homepage, https://gitlab.unige.ch/spice_dune/JADE
Project-URL: Issues, https://gitlab.unige.ch/spice_dune/JADE/-/issues
Classifier: Programming Language :: Python :: 3
Classifier: License :: OSI Approved :: GNU Lesser General Public License v3 or later (LGPLv3+)
Classifier: Operating System :: OS Independent
Requires-Python: >=3.8
License-File: LICENSE
Requires-Dist: numpy>=1.16
Requires-Dist: scipy
Requires-Dist: matplotlib
Requires-Dist: lmfit
Requires-Dist: astropy
Requires-Dist: emcee
Requires-Dist: pandas
Requires-Dist: jupyterlab
